{
    "uuid": [
        {
            "value": "e942d751-0211-449b-8e26-8bbe7c024ce5"
        }
    ],
    "langcode": [
        {
            "value": "en"
        }
    ],
    "uid": [],
    "filename": [
        {
            "value": "home-grown-herbs.jpg"
        }
    ],
    "uri": [
        {
            "value": "public:\/\/home-grown-herbs.jpg"
        }
    ],
    "filemime": [
        {
            "value": "image\/jpeg"
        }
    ],
    "filesize": [
        {
            "value": 114984
        }
    ],
    "status": [
        {
            "value": true
        }
    ],
    "created": [
        {
            "value": "2022-11-23T23:47:27+00:00",
            "format": "Y-m-d\\TH:i:sP"
        }
    ],
    "changed": [
        {
            "value": "2022-11-23T23:47:27+00:00",
            "format": "Y-m-d\\TH:i:sP"
        }
    ]
}